[
  {
    "id": 1,
    "name": "Escuela Nacional",
    "city": "CDMX"
  },
  {
    "id": 2,
    "name": "Instituto del Sureste",
    "city": "Villahermosa"
  },
  {
    "id": 3,
    "name": "Colegio Libre",
    "city": "Monterrey"
  },
  {
    "id": 4,
    "name": "Tec de Villaherosa",
    "city": "Villaherosa"
  },
  {
    "id": 5,
    "name": "Escuela de Pruebas",
    "city": "Testópolis"
  },
  {
    "id": 6,
    "name": "Escuela Actualizada",
    "city": "Ciudad Original"
  },
  {
    "id": 8,
    "name": "Colegio Test",
    "city": "Villahermosa",
    "region": "Sur"
  }
]